Phusion/__init__.py
Phusion/main.py
Phusion-0.0.1.data/data/LICENSE.md
Phusion-0.0.1.dist-info/LICENSE.md
Phusion-0.0.1.dist-info/METADATA
Phusion-0.0.1.dist-info/WHEEL
Phusion-0.0.1.dist-info/entry_points.txt
Phusion-0.0.1.dist-info/top_level.txt
Phusion-0.0.1.dist-info/RECORD
