Metadata-Version: 2.1
Name: Phusion
Version: 0.0.1
Summary: Python package used to aid with cocktail design.
Home-page: https://github.com/JoshuaIszatt
Author: Joshua Iszatt
Author-email: joshiszatt@gmail.com
License: AGPL-3.0
Requires-Python: >3
License-File: LICENSE.md
